dream_tools-4.1.4.dist-info/licenses/LICENSE
dreamtools/__init__.py
dreamtools/utils.py
dreamtools/gamY/__init__.py
dreamtools/gamY/classes.py
dreamtools/gamY/excel_endo_exo.py
dreamtools/gamY/extract_equations.py
dreamtools/gamY/extract_variables.py
dreamtools/gamY/gamY.py
dreamtools/gamY/gdx_to_excel.py
dreamtools/gamY/gekko_endo_exo.py
dreamtools/gamY/patterns.py
dreamtools/gamY/rename_set.py
dreamtools/gams_excel/__init__.py
dreamtools/gams_excel/excel_endo_exo.py
dreamtools/gams_excel/gams_excel.py
dreamtools/gams_excel/gdx_to_excel.py
dreamtools/gams_pandas/__init__.py
dreamtools/gams_pandas/gams_pandas.py
dreamtools/gams_pandas/gdx.py
dreamtools/gams_pandas/test_gams_pandas.py
dreamtools/gams_pandas/utility.py
dreamtools/multiindex_plotly/__init__.py
dreamtools/multiindex_plotly/age_plot.py
dreamtools/multiindex_plotly/dream_plotly_template.py
dreamtools/multiindex_plotly/dream_settings.py
dreamtools/multiindex_plotly/makro_settings.py
dreamtools/multiindex_plotly/plotly_util.py
dreamtools/multiindex_plotly/reporting.py
dreamtools/multiindex_plotly/scratch.py
dreamtools/multiindex_plotly/test_plot.py
dreamtools/multiindex_plotly/test_timeseries_analysis.py
dreamtools/multiindex_plotly/timeseries_analysis.py
dream_tools-4.1.4.dist-info/METADATA
dream_tools-4.1.4.dist-info/WHEEL
dream_tools-4.1.4.dist-info/top_level.txt
dream_tools-4.1.4.dist-info/RECORD
