Metadata-Version: 2.4
Name: dream-tools
Version: 4.1.4
Summary: A collection of tools used by the Danish Research Institute for Economic Analysis and Modelling, DREAM (https://dreamgruppen.dk/).
Home-page: https://github.com/MartinBonde/dream-tools
Author: Martin Kirk Bonde
Author-email: martin@bonde.dk
Classifier: Programming Language :: Python :: 3
Classifier: License :: OSI Approved :: MIT License
Requires-Python: >=3.6
License-File: LICENSE
Requires-Dist: pandas
Requires-Dist: numpy
Requires-Dist: plotly
Dynamic: author
Dynamic: author-email
Dynamic: classifier
Dynamic: description
Dynamic: description-content-type
Dynamic: home-page
Dynamic: license-file
Dynamic: requires-dist
Dynamic: requires-python
Dynamic: summary
